verified_numpy/__init__.py
verified_numpy/_version.py
verified_numpy/core.py
verified_numpy/py.typed
verified_numpy-0.1.0.dist-info/METADATA
verified_numpy-0.1.0.dist-info/WHEEL
verified_numpy-0.1.0.dist-info/licenses/LICENSE
verified_numpy-0.1.0.dist-info/RECORD
