Metadata-Version: 2.4
Name: verified-numpy
Version: 0.1.0
Summary: A robust verification wrapper for NumPy arrays using functional and contract paradigms.
Author-email: J-joon <jjkim030309@gmail.com>
License: MIT
License-File: LICENSE
Requires-Python: >=3.12
Requires-Dist: numpy
Requires-Dist: static-error-handler
Provides-Extra: dev
Requires-Dist: black; extra == 'dev'
Requires-Dist: coverage[toml]>=7; extra == 'dev'
Requires-Dist: hypothesis>=6.110; extra == 'dev'
Requires-Dist: mypy>=1.10; extra == 'dev'
Requires-Dist: pytest-cov>=5; extra == 'dev'
Requires-Dist: pytest>=8; extra == 'dev'
Requires-Dist: ruff>=0.6; extra == 'dev'
